clandestino_postgres/__init__.py
clandestino_postgres/infra.py
clandestino_postgres/ref.py
clandestino_postgres/repository.py
clandestino_postgres-0.1.1.dist-info/LICENSE
clandestino_postgres-0.1.1.dist-info/METADATA
clandestino_postgres-0.1.1.dist-info/WHEEL
clandestino_postgres-0.1.1.dist-info/RECORD
