Metadata-Version: 2.1
Name: clandestino-postgres
Version: 0.1.1
Summary: Clandestino Postgres implementation
Author: XimitGaia
Author-email: im.ximit@gmail.com
Requires-Python: >=3.11,<4.0
Classifier: Programming Language :: Python :: 3
Classifier: Programming Language :: Python :: 3.11
Requires-Dist: clandestino-interfaces (>=0.1.0,<0.2.0)
Requires-Dist: psycopg[binary] (>=3.1.18,<4.0.0)
Requires-Dist: python-decouple (>=3.8,<4.0)
